tinysaeasyconnector
