Metadata-Version: 2.1
Name: tinysaeasyconnector
Version: 0.1.1
Summary: Библиотека, которая облегчит подключение к TinySA
